cbadvanced/__init__.py
cbadvanced/auth.py
cbadvanced/client.py
cbadvanced/exceptions.py
cbadvanced/models.py
cbadvanced/py.typed
cbadvanced-3.0.2.dist-info/METADATA
cbadvanced-3.0.2.dist-info/WHEEL
cbadvanced-3.0.2.dist-info/licenses/LICENSE.md
cbadvanced-3.0.2.dist-info/RECORD
