Metadata-Version: 2.4
Name: cbadvanced
Version: 3.0.2
Summary: The unofficial Python client for the Coinbase Advanced Trade API
Project-URL: Homepage, https://github.com/mlindland/python-cbadvanced
Project-URL: Documentation, https://github.com/mlindland/python-cbadvanced#readme
Project-URL: Repository, https://github.com/mlindland/python-cbadvanced.git
Project-URL: Issues, https://github.com/mlindland/python-cbadvanced/issues
Project-URL: Changelog, https://github.com/mlindland/python-cbadvanced/blob/master/CHANGELOG.md
Author-email: Magnus Lindland <magnuslindland@proton.me>
License-Expression: MIT
License-File: LICENSE.md
Keywords: api,async,bitcoin,coinbase,coinbase-advanced,cryptocurrency,ethereum,httpx,trading,wrapper
Classifier: Development Status :: 4 - Beta
Classifier: Intended Audience :: Developers
Classifier: Intended Audience :: Financial and Insurance Industry
Classifier: License :: OSI Approved :: MIT License
Classifier: Operating System :: OS Independent
Classifier: Programming Language :: Python :: 3
Classifier: Programming Language :: Python :: 3.10
Classifier: Programming Language :: Python :: 3.11
Classifier: Programming Language :: Python :: 3.12
Classifier: Programming Language :: Python :: 3.13
Classifier: Topic :: Office/Business :: Financial :: Investment
Classifier: Topic :: Software Development :: Libraries :: Python Modules
Classifier: Typing :: Typed
Requires-Python: >=3.10
Requires-Dist: cryptography>=42.0
Requires-Dist: httpx>=0.27
Requires-Dist: pydantic>=2.0
Requires-Dist: pyjwt>=2.8
Provides-Extra: dev
Requires-Dist: mypy>=1.10; extra == 'dev'
Requires-Dist: pre-commit>=3.7; extra == 'dev'
Requires-Dist: pytest-asyncio>=0.23; extra == 'dev'
Requires-Dist: pytest-httpx>=0.30; extra == 'dev'
Requires-Dist: pytest>=8.0; extra == 'dev'
Requires-Dist: ruff>=0.5; extra == 'dev'
